ntype/__init__.py
ntype/ntype.py
ntype/version.py
ntype-0.0.1.dist-info/DESCRIPTION.rst
ntype-0.0.1.dist-info/METADATA
ntype-0.0.1.dist-info/RECORD
ntype-0.0.1.dist-info/WHEEL
ntype-0.0.1.dist-info/metadata.json
ntype-0.0.1.dist-info/top_level.txt
