Metadata-Version: 2.0
Name: ntype
Version: 0.0.1
Summary: Type Handler using NumPy
Home-page: UNKNOWN
Author: sahn
Author-email: jam31118@gmail.com
License: GPLv3
Keywords: type
Platform: UNKNOWN
Classifier: License :: OSI Approved :: GNU Affero General Public License v3
Classifier: Programming Language :: Python :: 3.5
Classifier: Programming Language :: Python :: 3.6
Requires-Dist: numpy
